[

//Industial Era
{
		"name": "Military Academy",
		"hurryCostModifier": 3,
		"Cost": 300
		"maintenance": 3,
		"requiredBuilding": "Armory"
                "greatPersonPoints": {"Great General": 1}
                "science": 2,
                "culture": 1,
		"uniques": [
			"New [Military] units start with [25] Experience [in this city]",
			"Destroyed when the city is captured",
			"[5] units cost no maintenance", 
			"[2] free [Musketmen] units appear",
			"Requires at least [12] population"
			]
		"requiredTech": "Military Science"
	},

]
